perftrackergt_elprogramadorgt/test.py
perftrackergt_elprogramadorgt-0.0.1.dist-info/LICENSE
perftrackergt_elprogramadorgt-0.0.1.dist-info/METADATA
perftrackergt_elprogramadorgt-0.0.1.dist-info/WHEEL
perftrackergt_elprogramadorgt-0.0.1.dist-info/top_level.txt
perftrackergt_elprogramadorgt-0.0.1.dist-info/RECORD
