Metadata-Version: 2.1
Name: perftrackergt_elprogramadorgt
Version: 0.0.1
Summary: Displays execution time and memory usage.
Author-email: Eduardo <elprogramadorgt8@gmail.com>
Project-URL: Homepage, https://github.com/elprogramadorgt/perftrackergt
Project-URL: Issues, https://github.com/elprogramadorgt/perftrackergt/issues
Classifier: Programming Language :: Python :: 3
Classifier: License :: OSI Approved :: MIT License
Classifier: Operating System :: OS Independent
Requires-Python: >=3.7
License-File: LICENSE
